simpleeval.py
simpleeval-1.0.2.dist-info/METADATA
simpleeval-1.0.2.dist-info/WHEEL
simpleeval-1.0.2.dist-info/licenses/LICENCE
simpleeval-1.0.2.dist-info/RECORD
