Metadata-Version: 2.3
Name: simpleeval
Version: 1.0.2
Summary: A simple, safe single expression evaluator library.
Project-URL: Source code, https://github.com/danthedeckie/simpleeval
Author-email: Daniel Fairhead <danthedeckie@gmail.com>
Maintainer-email: Daniel Fairhead <danthedeckie@gmail.com>
License-File: LICENCE
Keywords: ast,eval,expression,parse,simple
Classifier: Development Status :: 5 - Production/Stable
Classifier: Intended Audience :: Developers
Classifier: License :: OSI Approved :: MIT License
Classifier: Programming Language :: Python
Classifier: Topic :: Software Development :: Libraries :: Python Modules
Requires-Python: >=3.9
